findsamefile/__init__.py
findsamefile/find_same_find.py
findsamefile-0.0.1.dist-info/LICENSE
findsamefile-0.0.1.dist-info/METADATA
findsamefile-0.0.1.dist-info/WHEEL
findsamefile-0.0.1.dist-info/top_level.txt
findsamefile-0.0.1.dist-info/RECORD
