Metadata-Version: 2.1
Name: findsamefile
Version: 0.0.1
Summary: Python searches the same file based on md5
Home-page: https://github.com/Fgaoxing/find-same-file
Author: Fgaoxing
Author-email: Fgaoxing0206@163.com
License: UNKNOWN
Platform: UNKNOWN
Classifier: Programming Language :: Python :: 3
Classifier: License :: OSI Approved :: MIT License
Classifier: Operating System :: OS Independent
License-File: LICENSE
